semanticexecutor/__init__.py
semanticexecutor/semrun.py
semrun/__init__.py
semrun/semrun.py
semrun/semrun_base.py
semrun-0.0.2.dist-info/METADATA
semrun-0.0.2.dist-info/WHEEL
semrun-0.0.2.dist-info/top_level.txt
semrun-0.0.2.dist-info/RECORD
